[{
    "listName":"박물관",
    "list":[
    {   
        "imgName":"museum_01.png",
        "title":"부평역사박물관",
        "address":"인천시 부평구 굴포로 151",
        "text":"부평역사박물관은 부평의 역사와 문화를 바로 알리고 지역주민에게 정주의식을 함양시키고자 2007년 3월 29일에 개관하여 운영중입니다."
    },
    {
        "imgName":"museum_02.png",
        "title":"수도국산달동네박물관 ",
        "address":"인천시 동구 솔빛로 51",
        "text":"기억 속에서 잊혀져가는 수도국산달동네의 삶을 되살리고자 달동네 터에 박물관을 건립했습니다. 달동네 서민의 평범한 삶을 박물관의 주된 테마로 삼은 점은 우리나라 박물관의 역사에서도 이례적인 일이라고 합니다."
    },
    {
        "imgName":"museum_03.png",
        "title":"인천문화예술회관",
        "address":"인천시 남동구 예술로 149",
        "text":"공연장과 전시실, 회의실 등으로 이루어져 있고 공연장은 1,332석 규모의 대공연장과 486석의 소공연장, 440석의 야외공연장을 갖추고 있습니다. 전시실은 대전시실과 중앙전시실, 소전시실, 미추홀전시실로 이루어져 있습니다."
    },
    {
        "imgName":"museum_04.png",
        "title":"강화역사박물관",
        "address":"인천시 강화군 하점면 강화대로",
        "text":"전시할 목적으로 세워진 공립박물관입니다. 갑곶돈대 옆에 위치해 있다가 이전 개관했습니다. 상설전시실에는 강화의 선사시대 유적지와 고려왕릉에서 출토 된 유물이 전시되어 있습니다."
    },
    {   
        "imgName":"museum_05.png",
        "title":"중구생활사전시관",
        "address":"인천시 중구 신포로23번길 101",
        "text":"과거와 현재가 넘나드는 이곳, 역사와 문화가 공존하는 인천중구, 중구생활전시관은 대불호텔 전시관과 생활사전시관으로 되어 있습니다. 최초의 서양식 호텔을 소개하며, 인천중구의 생활사를 볼 수 있습니다."
    },
    {
        "imgName":"museum_06.png",
        "title":"인천개항박물관",
        "address":"인천시 중구 신포로23번길 89",
        "text":"과거와 현재가 넘나드는 이곳, 인천개항역사의 중심지에 자리 잡은 인천개항박물관은 개항기 인천을 통해 소개된 근대문화의 다양한 모습을 통해 개항이후 근대 인천의 면모를 학습할 수 있는 박물관입니다."
    },
    {
        "imgName":"museum_07.png",
        "title":"초콜릿문화박물관",
        "address":"인천시 연수구 능허대로 227-10",
        "text":"초콜릿에 대한 세계사와 문화 발전사에 관한 조형물,벽화,유뮬,도자기 등을 통해 재미있게 이해할 수 있으며 AR존에서는 초콜릿이라는 단순 주제를, 체험학습 장에서는 달콤한 초콜릿을 직접 만드는 공간입니다."
    },
    {
        "imgName":"museum_08.png",
        "title":"인천학생과학관",
        "address":"인천시 중구 영종대로 277번길",
        "text":"학교 현장의 과학교육 전문성 지원, 과학마인드 확산을 위해 인천학생과학관을 운영하고 있으며, 인천학생과학관은 꿈돌이관, 자연사탐구관, 기초과학체험관, 미래과학관, 과학체험관의 5개 전시관으로 구성되어있습니다."
    }
    ]
}]